healthcheckbot/__init__.py
healthcheckbot/app.py
healthcheckbot/assertions.py
healthcheckbot/cli.py
healthcheckbot/outputs.py
healthcheckbot/triggers.py
healthcheckbot/version.py
healthcheckbot/watchers.py
healthcheckbot/common/__init__.py
healthcheckbot/common/bootstrap.py
healthcheckbot/common/core.py
healthcheckbot/common/error.py
healthcheckbot/common/evaluator.py
healthcheckbot/common/model.py
healthcheckbot/common/utils.py
healthcheckbot/common/validators.py
healthcheckbot/contrib/__init__.py
healthcheckbot/contrib/postgres.py
healthcheckbot/contrib/celery/__init__.py
healthcheckbot/contrib/celery/redis.py
healthcheckbot-0.3.6.dist-info/METADATA
healthcheckbot-0.3.6.dist-info/WHEEL
healthcheckbot-0.3.6.dist-info/entry_points.txt
healthcheckbot-0.3.6.dist-info/top_level.txt
healthcheckbot-0.3.6.dist-info/RECORD
