Metadata-Version: 2.1
Name: healthcheckbot
Version: 0.3.6
Summary: Robust way to setup external health checks for your software
Home-page: https://githib.com/Logicify/healthcheckbot
Author: Dmitry Berezovsky
License: GPLv3
Keywords: python healthchecks assertion validate health server healthcheck
Platform: UNKNOWN
Classifier: Development Status :: 3 - Alpha
Classifier: Intended Audience :: Developers
Classifier: Topic :: Software Development :: Build Tools
Classifier: License :: OSI Approved :: GNU General Public License v3 (GPLv3)
Classifier: Programming Language :: Python :: 3
Classifier: Programming Language :: Python :: 3.6
Requires-Dist: PyYAML (==4.2b1)
Requires-Dist: typing (>=3.6)
Requires-Dist: requests (==2.21.0)
Requires-Dist: beautifulsoup4 (==4.4.0)
Requires-Dist: graypy (==0.3.2)
Requires-Dist: daemons (==1.3.0)
Provides-Extra: dev
Provides-Extra: test
